chrome_profile_manager/__init__.py
chrome_profile_manager/__main__.py
chrome_profile_manager/main.py
chrome_profile_manager/config/__init__.py
chrome_profile_manager/config/settings.py
chrome_profile_manager/helpers/__init__.py
chrome_profile_manager/helpers/alias_creator.py
chrome_profile_manager/utils/__init__.py
chrome_profile_manager/utils/chrome_scanner.py
pybro_cli-0.1.8.dist-info/METADATA
pybro_cli-0.1.8.dist-info/WHEEL
pybro_cli-0.1.8.dist-info/entry_points.txt
pybro_cli-0.1.8.dist-info/top_level.txt
pybro_cli-0.1.8.dist-info/RECORD
