Metadata-Version: 2.1
Name: pybro-cli
Version: 0.1.8
Summary: 🔥 PyBro CLI - A Collection of Python Dev Tools for Debian 24.04
Home-page: https://github.com/iTrauco/pybro
Author: Chris Trauco
Author-email: dev@trau.co
Keywords: cli,chrome,profile,manager,debian,linux,development,tools
Classifier: Programming Language :: Python :: 3
Classifier: License :: OSI Approved :: MIT License
Classifier: Operating System :: POSIX :: Linux
Classifier: Environment :: Console
Classifier: Topic :: Utilities
Classifier: Development Status :: 3 - Alpha
Requires-Python: >=3.8
Requires-Dist: rich>=10.0.0
Requires-Dist: pathlib>=1.0.1
Requires-Dist: typing>=3.7.4
